OCR_aadhar/SQLite_Python.db
OCR_aadhar/__init__.py
OCR_aadhar-0.0.1.dist-info/LICENSE.txt
OCR_aadhar-0.0.1.dist-info/METADATA
OCR_aadhar-0.0.1.dist-info/WHEEL
OCR_aadhar-0.0.1.dist-info/top_level.txt
OCR_aadhar-0.0.1.dist-info/RECORD
