Metadata-Version: 2.1
Name: OCR-aadhar
Version: 0.0.1
Summary: Aadhar attributes Features recognition dataset with annotations.
Home-page: https://github.com/adarsh1mehra/OCR-aadhar
Author: ADARSH KISHORE MEHRA
Author-email: adarsh.mehra800@gmail.com
License: MIT License
Platform: UNKNOWN
